restic_exporter/__init__.py
restic_exporter/restic_exporter.py
restic_exporter-0.0.2.dist-info/LICENSE
restic_exporter-0.0.2.dist-info/METADATA
restic_exporter-0.0.2.dist-info/WHEEL
restic_exporter-0.0.2.dist-info/top_level.txt
restic_exporter-0.0.2.dist-info/RECORD
