Metadata-Version: 2.1
Name: restic-exporter
Version: 0.0.2
Summary: Statistic exporter for restic backups
Home-page: https://github.com/dermotduffy/restic-exporter
Author: Dermot Duffy
Author-email: dermot.duffy@gmail.com
License: UNKNOWN
Keywords: restic backup statistics
Platform: any
Classifier: Intended Audience :: Developers
Classifier: Programming Language :: Python :: 3.7
Classifier: Programming Language :: Python :: 3.8
Classifier: Programming Language :: Python :: 3.9
Classifier: License :: OSI Approved :: MIT License
Classifier: Operating System :: OS Independent
Classifier: Topic :: System :: Archiving :: Backup
Classifier: Topic :: System :: Monitoring
Requires-Python: >=3.7
